dockonsurf/ASANN.py
dockonsurf/__init__.py
dockonsurf/calculation.py
dockonsurf/clustering.py
dockonsurf/config_arg.py
dockonsurf/config_log.py
dockonsurf/dockonsurf.py
dockonsurf/dos_input.py
dockonsurf/formats.py
dockonsurf/internal_rotate.py
dockonsurf/isolated.py
dockonsurf/refinement.py
dockonsurf/screening.py
dockonsurf/utilities.py
dockonsurf/xyz2mol.py
dockonsurf-0.0.1.dist-info/LICENSE
dockonsurf-0.0.1.dist-info/METADATA
dockonsurf-0.0.1.dist-info/WHEEL
dockonsurf-0.0.1.dist-info/top_level.txt
dockonsurf-0.0.1.dist-info/RECORD
