Metadata-Version: 2.1
Name: dockonsurf
Version: 0.0.1
Summary: Code to systematically find the most stable geometry for molecules on surfaces
Home-page: http://forge.cbp.ens-lyon.fr/redmine/projects/dockonsurf
Author: Carles Martí
Author-email: carles.marti2@gmail.com
License: UNKNOWN
Project-URL: Documentation, https://dockonsurf.readthedocs.io
Platform: UNKNOWN
Classifier: Development Status :: 4 - Beta
Classifier: Environment :: Console
Classifier: Intended Audience :: Science/Research
Classifier: License :: OSI Approved :: MIT License
Classifier: Natural Language :: English
Classifier: Operating System :: OS Independent
Classifier: Programming Language :: Python :: 3
Classifier: Programming Language :: Python :: 3.6
Classifier: Topic :: Scientific/Engineering :: Chemistry
Requires-Python: >=3.6
License-File: LICENSE
Requires-Dist: ase (>=3.19.1)
Requires-Dist: hdbscan (~=0.8.26)
Requires-Dist: matplotlib (>=3.2.1)
Requires-Dist: networkx (>=2.4)
Requires-Dist: numpy (>=1.16.6)
Requires-Dist: pycp2k (~=0.2.2)
Requires-Dist: pymatgen (~=2020.11.11)
Requires-Dist: python-daemon (~=2.2.4)
Requires-Dist: rdkit (>=2019.9.3)
Requires-Dist: scikit-learn (~=0.23.1)
